strand/__init__.py
strand-0.0.2.dist-info/LICENSE
strand-0.0.2.dist-info/METADATA
strand-0.0.2.dist-info/WHEEL
strand-0.0.2.dist-info/top_level.txt
strand-0.0.2.dist-info/RECORD
