Metadata-Version: 2.1
Name: strand
Version: 0.0.2
Summary: Easy creation of non-blocking tasks
Home-page: https://github.com/i2mint/strand
Author: OtoSense
License: apache-2.0
Platform: any
